pylpex/__init__.py
pylpex/interpreter.py
pylpex/main.py
pylpex/typesystem.py
pylpex/evaluator/__init__.py
pylpex/evaluator/builtin.py
pylpex/evaluator/core.py
pylpex/evaluator/environment.py
pylpex/evaluator/exception.py
pylpex/evaluator/expressions.py
pylpex/evaluator/operators.py
pylpex/evaluator/statements.py
pylpex/evaluator/variables.py
pylpex/evaluator/visitor.py
pylpex/lexer/__init__.py
pylpex/lexer/core.py
pylpex/lexer/tokens.py
pylpex/parser/ASTNodes.py
pylpex/parser/__init__.py
pylpex/parser/base.py
pylpex/parser/core.py
pylpex/parser/expressions.py
pylpex/parser/functions.py
pylpex/parser/statements.py
pylpex/parser/structures.py
pylpex/utils/ASTprinter.py
pylpex/utils/__init__.py
pylpex/utils/shortcuts.py
pylpex-1.1.4.dist-info/licenses/LICENSE.txt
pylpex-1.1.4.dist-info/METADATA
pylpex-1.1.4.dist-info/WHEEL
pylpex-1.1.4.dist-info/entry_points.txt
pylpex-1.1.4.dist-info/top_level.txt
pylpex-1.1.4.dist-info/RECORD
