Metadata-Version: 2.4
Name: pylpex
Version: 1.1.4
Summary: Langage de programmation expérimental inspiré de Python.
Author-email: Guillaume Foucaud <guillaumefoucaudmath@gmail.com>
License-Expression: MIT
Classifier: Programming Language :: Python :: 3
Classifier: Operating System :: OS Independent
Requires-Python: >=3.13
License-File: LICENSE.txt
Requires-Dist: ipykernel>=7.0.1
Dynamic: license-file
